{
    "enums": {
        
    },
    "classes": {
        "Resources": {
            "is_public": false,
            "is_Sealed": true,
            "properties": {
            },
            "methods": {
                "GetInstance": {
                    "is_public": false,
                    "is_static": true
                },
                "GetResourcesCount": {
                    "is_public": false
                },
                "Clear": {
                    "is_public": false
                },
                "Reload": {
                    "is_public": false
                }
            }
        }
    }
}